{
  "issue": 772,
  "date": "2021-09-18",
  "audio": "https://cdn.radio-t.com/rt_podcast772.mp3",
  "cover": "https://radio-t.com/images/radio-t/rt772.jpg",
  "start_time": 0,
  "topics": [
    {
      "id": "000000000000000000000000",
      "title": "Ушел Sir Clive Sinclair",
      "links": [
        "https://www.theguardian.com/technology/2021/sep/16/home-computing-pioneer-sir-clive-sinclair-dies-aged-81"
      ],
      "time": "00:03:17"
    },
    {
      "id": "000000000000000000000000",
      "title": "Что Apple показали на этот раз",
      "links": [
        "https://gizmodo.com/heres-everything-apple-announced-during-its-iphone-13-e-1847675697"
      ],
      "time": "00:11:47"
    },
    {
      "id": "000000000000000000000000",
      "title": "Apple и Google удалили приложение Навального",
      "links": [
        "https://www.nytimes.com/2021/09/17/world/europe/russia-navalny-app-election.html"
      ],
      "time": "01:05:35"
    },
    {
      "id": "000000000000000000000000",
      "title": "Дуров имеет про это сказать пару слов",
      "links": [
        "https://t.me/durov_russia/32"
      ],
      "time": "01:15:12"
    },
    {
      "id": "000000000000000000000000",
      "title": "Гитлаб выходит на IPO",
      "links": [
        "https://www.cnbc.com/2021/09/17/github-rival-gitlab-files-to-go-public-on-revenue-over-200-million.html"
      ],
      "time": "01:37:52"
    },
    {
      "id": "000000000000000000000000",
      "title": "Насколько быстра Java 17?",
      "links": [
        "https://www.optaplanner.org/blog/2021/09/15/HowMuchFasterIsJava17.html"
      ],
      "time": "01:49:30"
    },
    {
      "id": "000000000000000000000000",
      "title": "Xiaomi Smart Glasses",
      "links": [
        "https://blog.mi.com/en/2021/09/14/xiaomi-unveils-xiaomi-smart-glasses/"
      ],
      "time": "01:58:55"
    },
    {
      "id": "000000000000000000000000",
      "title": "Темы слушателей",
      "links": [
        "https://radio-t.com/p/2021/09/14/prep-772/"
      ],
      "time": "02:08:11"
    }
  ],
  "tags": null
}