{
  "issue": 117,
  "date": "2008-12-21",
  "audio": "https://cdn.radio-t.com/rt_podcast117.mp3",
  "cover": "https://radio-t.com/images/radio-t/rt117.jpg",
  "start_time": 0,
  "topics": [
    {
      "id": "000000000000000000000000",
      "title": "Предновогодние железки для радости",
      "links": [],
      "time": ""
    },
    {
      "id": "000000000000000000000000",
      "title": "Почему Gmail лучше всех",
      "links": [],
      "time": ""
    },
    {
      "id": "000000000000000000000000",
      "title": "ЯП и религии",
      "links": [],
      "time": ""
    },
    {
      "id": "000000000000000000000000",
      "title": "WiFi подобен вирусу",
      "links": [],
      "time": ""
    },
    {
      "id": "000000000000000000000000",
      "title": "Пора отказаться от IE",
      "links": [],
      "time": ""
    },
    {
      "id": "000000000000000000000000",
      "title": "Шторм везде. Ликом страшен",
      "links": [],
      "time": ""
    },
    {
      "id": "000000000000000000000000",
      "title": "Свобода музыки подходит",
      "links": [],
      "time": ""
    },
    {
      "id": "000000000000000000000000",
      "title": "Новый web.py и возможная Nova",
      "links": [],
      "time": ""
    },
    {
      "id": "000000000000000000000000",
      "title": "Темы наших слушателей",
      "links": [],
      "time": ""
    }
  ],
  "tags": null
}