{
  "issue": 137,
  "date": "2009-05-17",
  "audio": "https://cdn.radio-t.com/rt_podcast137.mp3",
  "cover": "https://radio-t.com/images/radio-t/rt137.png",
  "start_time": 0,
  "topics": [
    {
      "id": "000000000000000000000000",
      "title": "Сбой Гугла с глобальным эффектом",
      "links": [
        "http://net.compulenta.ru/426372/"
      ],
      "time": ""
    },
    {
      "id": "000000000000000000000000",
      "title": "Гарантии на программы в Европе",
      "links": [
        "http://www.linux.org.ru/view-message.jsp?msgid=3693981"
      ],
      "time": ""
    },
    {
      "id": "000000000000000000000000",
      "title": "Гаджет этой недели от onegadget.ru",
      "links": [
        "http://onegadget.ru/og/3821"
      ],
      "time": ""
    },
    {
      "id": "000000000000000000000000",
      "title": "iPod с вентилятором, но для читателй",
      "links": [
        "http://www.engadget.com/2009/05/14/intereads-cool-er-claims-to-be-the-ipod-moment-for-e-readers/"
      ],
      "time": ""
    },
    {
      "id": "000000000000000000000000",
      "title": "Русский “мак” из первых рук",
      "links": [],
      "time": ""
    },
    {
      "id": "000000000000000000000000",
      "title": "Анализ поиска от Яндекса",
      "links": [
        "http://net.compulenta.ru/426170/"
      ],
      "time": ""
    },
    {
      "id": "000000000000000000000000",
      "title": "Microsoft опять против iTunes",
      "links": [
        "http://habrahabr.ru/blogs/microsoft/59480/"
      ],
      "time": ""
    },
    {
      "id": "000000000000000000000000",
      "title": "Wolfram хорош до удивления",
      "links": [
        "http://f055.net/article/wolframalpha-launching-today-and-what-it-means-for-google-and-search/"
      ],
      "time": ""
    },
    {
      "id": "000000000000000000000000",
      "title": "Twitter меняет @reply: все не так просто",
      "links": [
        "http://habrahabr.ru/blogs/twitter/59497/"
      ],
      "time": ""
    }
  ],
  "tags": null
}