{
  "issue": 436,
  "date": "2015-03-21",
  "audio": "https://cdn.radio-t.com/rt_podcast436.mp3",
  "cover": "https://radio-t.com/images/radio-t/rt436.jpg",
  "start_time": 0,
  "topics": [
    {
      "id": "000000000000000000000000",
      "title": "Опять новый Apple TV.",
      "links": [
        "http://prsm.tc/wVTUTB"
      ],
      "time": ""
    },
    {
      "id": "000000000000000000000000",
      "title": "Amazon опробует дроны.",
      "links": [
        "http://prsm.tc/BDNKJ8"
      ],
      "time": ""
    },
    {
      "id": "000000000000000000000000",
      "title": "Google теперь проверяет Android программы.",
      "links": [
        "http://www.theverge.com/2015/3/17/8231125/android-apps-now-reviewed-by-google"
      ],
      "time": ""
    },
    {
      "id": "000000000000000000000000",
      "title": "Ночной кошмар для Linux на декстопе.",
      "links": [
        "http://www.extremetech.com/extreme/201722-linuxs-worst-case-scenario-microsoft-makes-secure-boot-mandatory-locks-out-other-opera"
      ],
      "time": ""
    },
    {
      "id": "000000000000000000000000",
      "title": "Yahoo показала Password-Free Login.",
      "links": [
        "http://social.techcrunch.com/2015/03/16/yahoo-introduces-password-free-login-just-dont-lose-your-phone/"
      ],
      "time": ""
    },
    {
      "id": "000000000000000000000000",
      "title": "Microsoft превратит Android в Windows 10.",
      "links": [
        "http://social.techcrunch.com/2015/03/17/microsoft-android-rom/"
      ],
      "time": ""
    },
    {
      "id": "000000000000000000000000",
      "title": "Amazon ELB — еще лучше, еще больше.",
      "links": [
        "http://www.datacenterknowledge.com/archives/2015/03/19/amazon-web-services-beefs-elastic-block-store/"
      ],
      "time": ""
    },
    {
      "id": "000000000000000000000000",
      "title": "Windows 10 и для пиратов.",
      "links": [
        "http://www.computerworld.com/article/2898803/microsoft-takes-extraordinary-step-will-give-pirates-free-windows-10-upgrade.html"
      ],
      "time": ""
    },
    {
      "id": "000000000000000000000000",
      "title": "Docker в IntelliJ IDEA 14.1.",
      "links": [
        "http://prsm.tc/saT1lB"
      ],
      "time": ""
    },
    {
      "id": "000000000000000000000000",
      "title": "Разбираемся в деталях нового архива.",
      "links": [
        "http://www.forbes.com/sites/benkepes/2015/03/20/getting-some-clarity-on-the-google-versus-amazon-archival-storage-products/"
      ],
      "time": ""
    },
    {
      "id": "000000000000000000000000",
      "title": "Amazon RDS с PostgreSQL 9.4.1.",
      "links": [
        "https://aws.amazon.com/blogs/aws/amazon-rds-update-postgresql-9-4-1-now-available/"
      ],
      "time": ""
    },
    {
      "id": "000000000000000000000000",
      "title": "Шутки и издевательства по поводу Retina MacBook.",
      "links": [
        "http://prsm.tc/6fHmPJ"
      ],
      "time": ""
    },
    {
      "id": "000000000000000000000000",
      "title": "Темы наших слушателей.",
      "links": [],
      "time": ""
    }
  ],
  "tags": null
}