{
  "issue": 89,
  "date": "2008-06-09",
  "audio": "https://cdn.radio-t.com/rt_podcast89.mp3",
  "cover": "",
  "start_time": 0,
  "topics": [
    {
      "id": "000000000000000000000000",
      "title": "Китайские хулиганы против нашего электричества",
      "links": [
        "http://webplanet.ru/node/19626"
      ],
      "time": ""
    },
    {
      "id": "000000000000000000000000",
      "title": "С днем рожденья, х86",
      "links": [
        "http://hardware.slashdot.org/article.pl?sid=08/06/05/1247249\u0026from=rss"
      ],
      "time": ""
    },
    {
      "id": "000000000000000000000000",
      "title": "Palm, но на Windows",
      "links": [
        "http://feeds.engadget.com/%7Er/weblogsinc/engadget/%7E3/305312379/"
      ],
      "time": ""
    },
    {
      "id": "000000000000000000000000",
      "title": "Телефон за копейки",
      "links": [
        "http://lenta.com.ua/124517.html"
      ],
      "time": ""
    },
    {
      "id": "000000000000000000000000",
      "title": "Еее на столе",
      "links": [
        "http://webplanet.ru/news/gadgets/2008/06/06/eeebox.html"
      ],
      "time": ""
    },
    {
      "id": "000000000000000000000000",
      "title": "Забавная ненависть к линукс",
      "links": [
        "http://www.razgovor.org/special/article588/"
      ],
      "time": ""
    },
    {
      "id": "000000000000000000000000",
      "title": "Телевизор выходит в сеть",
      "links": [
        "http://www.crunchgear.com/2008/06/05/sony-launches-new-line-for-high-end-hdtvs-loaded-with-features/"
      ],
      "time": ""
    },
    {
      "id": "000000000000000000000000",
      "title": "Что сказал Линус",
      "links": [
        "http://www.opennet.ru/opennews/art.shtml?num=16343"
      ],
      "time": ""
    },
    {
      "id": "000000000000000000000000",
      "title": "Новинки от Adobe",
      "links": [
        "http://weblogs.macromedia.com/labs/archives/2008/06/new_dreamweaver_fireworks_and_soundbooth_betas_released_on_labs.html"
      ],
      "time": ""
    },
    {
      "id": "000000000000000000000000",
      "title": "Twitter-\"убийца\", опять",
      "links": [
        "http://internetno.net/2008/06/03/plurk-review/"
      ],
      "time": ""
    },
    {
      "id": "000000000000000000000000",
      "title": "Пираты против новых видео технологий",
      "links": [
        "http://webplanet.ru/news/law/2008/06/04/bluray.html"
      ],
      "time": ""
    },
    {
      "id": "000000000000000000000000",
      "title": "IM нам в помощь",
      "links": [
        "http://www.businesspress.ru/newspaper/article_mId_37_aId_450093.html"
      ],
      "time": ""
    },
    {
      "id": "000000000000000000000000",
      "title": "Новый поисковик пугает Яндекс и Google",
      "links": [
        "http://webplanet.ru/news/service/2008/06/04/wikia.html"
      ],
      "time": ""
    },
    {
      "id": "000000000000000000000000",
      "title": "Темы(/p/2008/06/03/prep-89/) наших слушателей",
      "links": [],
      "time": ""
    }
  ],
  "tags": null
}