{
  "issue": 560,
  "date": "2017-08-26",
  "audio": "https://cdn.radio-t.com/rt_podcast560.mp3",
  "cover": "https://radio-t.com/images/radio-t/rt560.jpg",
  "start_time": 0,
  "topics": [
    {
      "id": "000000000000000000000000",
      "title": "10 лет хэштегу",
      "links": [
        "https://thenextweb.com/socialmedia/2017/08/23/the-hashtag-is-ten/"
      ],
      "time": "00:02:41"
    },
    {
      "id": "000000000000000000000000",
      "title": "Windows 95 живет 22 года",
      "links": [
        "https://thenextweb.com/insider/2017/08/24/windows-95-22-years-old-today-lets-hope-doesnt-turn-23/"
      ],
      "time": "00:06:56"
    },
    {
      "id": "000000000000000000000000",
      "title": "Драма вокруг Node.js",
      "links": [
        "http://www.zdnet.com/article/after-governance-breakdown-node-js-leaders-fight-for-its-survival/"
      ],
      "time": "00:13:38"
    },
    {
      "id": "000000000000000000000000",
      "title": "Тест неограниченного хранилища Amazon",
      "links": [
        "https://motherboard.vice.com/en_us/article/a33j5a/a-redditor-archived-nearly-2-million-gigabytes-of-porn-to-test-amazons-unlimited-cloud-storage"
      ],
      "time": "00:31:38"
    },
    {
      "id": "000000000000000000000000",
      "title": "Go 1.9",
      "links": [
        "https://blog.golang.org/go1.9"
      ],
      "time": "00:38:02"
    },
    {
      "id": "000000000000000000000000",
      "title": "DO Spaces",
      "links": [
        "https://gist.github.com/eliza411/cd89640a13769cd8d3b11140062e1c7b"
      ],
      "time": "00:57:39"
    },
    {
      "id": "000000000000000000000000",
      "title": "Google и миллионы плохих картинок",
      "links": [
        "https://techcrunch.com/2017/08/25/google-releases-millions-of-bad-drawings-for-you-and-your-ai-to-paw-through/"
      ],
      "time": "01:03:45"
    },
    {
      "id": "000000000000000000000000",
      "title": "Apple TV проигрывает рынок",
      "links": [
        "https://www.theverge.com/circuitbreaker/2017/8/23/16194190/apple-tv-losing-marketshare-roku-amazon-survey"
      ],
      "time": "01:08:51"
    },
    {
      "id": "000000000000000000000000",
      "title": "Android — 8.0 Oreo",
      "links": [
        "https://www.android.com/versions/oreo-8-0/"
      ],
      "time": "01:30:43"
    },
    {
      "id": "000000000000000000000000",
      "title": "Темы наших",
      "links": [],
      "time": ""
    }
  ],
  "tags": null
}