{
  "issue": 760,
  "date": "2021-06-26",
  "audio": "https://cdn.radio-t.com/rt_podcast760.mp3",
  "cover": "https://radio-t.com/images/radio-t/rt760.jpg",
  "start_time": 0,
  "topics": [
    {
      "id": "000000000000000000000000",
      "title": "Microsoft объявила Windows 11",
      "links": [
        "https://www.theverge.com/2021/6/24/22546791/microsoft-windows-11-announcement-features-updates"
      ],
      "time": "00:01:47"
    },
    {
      "id": "000000000000000000000000",
      "title": "Программы для Android на Windows 11",
      "links": [
        "https://www.theverge.com/2021/6/24/22548428/microsoft-windows-11-android-apps-support-amazon-store"
      ],
      "time": "00:11:52"
    },
    {
      "id": "000000000000000000000000",
      "title": "Android TV с рекламой",
      "links": [
        "https://play.google.com/store/apps/details?id=com.google.android.tvlauncher"
      ],
      "time": "00:30:20"
    },
    {
      "id": "000000000000000000000000",
      "title": "Этика против темных дел",
      "links": [
        "https://www.peachesnstink.com/p/6pJoCuczOj8cxCUQDMlfQv"
      ],
      "time": "00:37:43"
    },
    {
      "id": "000000000000000000000000",
      "title": "Злые программисты портят безопасность",
      "links": [
        "https://www.theregister.com/2021/06/25/application_vulnerability_epidemic/"
      ],
      "time": "00:56:24"
    },
    {
      "id": "000000000000000000000000",
      "title": "WD My Book Live превратился в тыкву",
      "links": [
        "https://arstechnica.com/gadgets/2021/06/mass-data-wipe-in-my-book-devices-prompts-warning-from-western-digital/"
      ],
      "time": "01:19:18"
    },
    {
      "id": "000000000000000000000000",
      "title": "Проект Brave начал тестирование поисковой системы",
      "links": [
        "https://www.opennet.ru/opennews/art.shtml?num=55376"
      ],
      "time": "01:28:41"
    },
    {
      "id": "000000000000000000000000",
      "title": "KPI не понравился",
      "links": [
        "https://lkml.org/lkml/2021/6/18/153"
      ],
      "time": "01:40:12"
    },
    {
      "id": "000000000000000000000000",
      "title": "Micro - все банальное как сервис",
      "links": [
        "https://blog.m3o.com/2021/06/24/micro-apis-for-everyday-use.html"
      ],
      "time": "01:51:54"
    },
    {
      "id": "000000000000000000000000",
      "title": "Темы слушателей",
      "links": [
        "https://radio-t.com/p/2021/06/22/prep-760/"
      ],
      "time": "02:02:30"
    }
  ],
  "tags": null
}