{
  "issue": 789,
  "date": "2022-01-15",
  "audio": "https://cdn.radio-t.com/rt_podcast789.mp3",
  "cover": "https://radio-t.com/images/radio-t/rt789.jpg",
  "start_time": 1642278454,
  "topics": [
    {
      "id": "000000000000000000000000",
      "title": "GitHub Copilot может странное",
      "links": [
        "https://dagshub.com/blog/github-copilot-not-code/"
      ],
      "time": "00:05:40"
    },
    {
      "id": "000000000000000000000000",
      "title": "Как гугл, но для GitHub",
      "links": [
        "https://github.blog/2021-12-08-improving-github-code-search/"
      ],
      "time": "00:14:59"
    },
    {
      "id": "000000000000000000000000",
      "title": "Пишите плохой код",
      "links": [
        "https://www.cyclic.sh/posts/write-shitty-code"
      ],
      "time": "00:25:33"
    },
    {
      "id": "000000000000000000000000",
      "title": "Keychron Q2",
      "links": [
        "https://www.theverge.com/22877979/keychron-q2-review?utm_campaign=theverge"
      ],
      "time": "00:59:05"
    },
    {
      "id": "000000000000000000000000",
      "title": "IT — не для всех",
      "links": [
        "https://habr.com/ru/post/599207/"
      ],
      "time": "01:15:37"
    },
    {
      "id": "000000000000000000000000",
      "title": "PayPal теперь накажут",
      "links": [
        "https://www.engadget.com/paypal-lawsuit-freezing-customer-accounts-funds-073128563.html"
      ],
      "time": "01:51:29"
    },
    {
      "id": "000000000000000000000000",
      "title": "Темы слушателей",
      "links": [
        "https://radio-t.com/p/2022/01/11/prep-789/"
      ],
      "time": "02:01:51"
    }
  ],
  "tags": null
}