{
  "issue": 525,
  "date": "2016-12-10",
  "audio": "https://cdn.radio-t.com/rt_podcast525.mp3",
  "cover": "https://radio-t.com/images/radio-t/rt525.jpg",
  "start_time": 1481401108,
  "topics": [
    {
      "id": "000000000000000000000000",
      "title": "Samsung против Note 7",
      "links": [
        "http://www.theverge.com/circuitbreaker/2016/12/9/13897794/samsung-galaxy-note-7-update-shut-down-inoperable"
      ],
      "time": "00:15:38"
    },
    {
      "id": "000000000000000000000000",
      "title": "TIOBE Index конца 2016",
      "links": [
        "http://www.tiobe.com/tiobe-index/"
      ],
      "time": "00:24:11"
    },
    {
      "id": "000000000000000000000000",
      "title": "Python 2.8",
      "links": [
        "https://www.naftaliharris.com/blog/why-making-python-2.8/"
      ],
      "time": "00:31:52"
    },
    {
      "id": "000000000000000000000000",
      "title": "Как платить программистам меньше",
      "links": [
        "https://habrahabr.ru/post/317164/"
      ],
      "time": "00:38:14"
    },
    {
      "id": "000000000000000000000000",
      "title": "Опасности личных проектов",
      "links": [
        "https://www.joelonsoftware.com/2016/12/09/developers-side-projects/"
      ],
      "time": "01:11:12"
    },
    {
      "id": "000000000000000000000000",
      "title": "Occipital за $399 для iPhone",
      "links": [
        "https://techcrunch.com/2016/12/09/occipital-shows-off-a-399-mixed-reality-headset-for-iphone/"
      ],
      "time": "01:25:05"
    },
    {
      "id": "000000000000000000000000",
      "title": "Microsoft сделает это из телефона",
      "links": [
        "http://www.theverge.com/2016/12/8/13881930/microsoft-turn-a-phone-into-a-pc-arm-continuum"
      ],
      "time": "01:41:59"
    },
    {
      "id": "000000000000000000000000",
      "title": "Amazon магазин в оффлайне",
      "links": [
        "http://mashable.com/2016/12/05/amazon-go-shopping/"
      ],
      "time": "01:50:24"
    },
    {
      "id": "000000000000000000000000",
      "title": "Темы наших слушателей",
      "links": [],
      "time": ""
    }
  ],
  "tags": null
}